okex/__init__.py
okex/context.py
okex/core.py
okex/helpers.py
okex-0.1.6.dist-info/DESCRIPTION.rst
okex-0.1.6.dist-info/METADATA
okex-0.1.6.dist-info/RECORD
okex-0.1.6.dist-info/WHEEL
okex-0.1.6.dist-info/metadata.json
okex-0.1.6.dist-info/top_level.txt
