Metadata-Version: 1.1
Name: okex
Version: 0.1.6
Summary: OKEX API SDK
Home-page: https://github.com/bopo/okex
Author: Bopo Wang
Author-email: ibopo@126.com
License: Copyright (c) 2017, Kenneth Reitz
